{"created":1337640081,"modified":1337640081,"expires":1353541281,"data":{"has_trackers":true,"plural_attendees":true,"dates_with_html5":"<time class=\"dtstart\" datetime=\"2012-06-09\">9th June 2012<\/time>","plural_speakers":false,"has_attendees":true,"year":2012,"speakers_version":41,"id":"cfmyt","place_name":"Birmingham, England","has_speakers":false,"plural_trackers":true,"sxsw_special_case":false,"version":41,"num_trackers":9,"start_date":"2012-06-09","num_speakers":0,"end_date":"2012-06-09","is_online":false,"slug":"multipack-june","dates":"9th June 2012","name":"Multipack Birmingham: June","has_place":true,"place":{"name":"Birmingham, England","id":"birmingham"},"num_attendees":2,"tagline":"Come for a drink, and a bite to eat with one of the friendliest communities of web professionals, geeks and techies from across the West Midlands, to discuss code, standards, technology, and share our knowledge and experiences.","attendees_version":41,"sessions_version":41}}